outputs/__init__.py
outputs-1.14.dist-info/LICENSE
outputs-1.14.dist-info/METADATA
outputs-1.14.dist-info/WHEEL
outputs-1.14.dist-info/top_level.txt
outputs-1.14.dist-info/RECORD
