Metadata-Version: 2.1
Name: outputs
Version: 1.14
Summary: This is a Python library designed to extend CLI printing functionalities, primarily focusing on logging features similar to logging, but also exploring other directions. Additionally, it supports a high-fidelity style akin to PinkShell.
Author-email: Pinpe <813233375@qq.com>
Project-URL: blog-url, https://pinpe.top
Classifier: Programming Language :: Python :: 3
Classifier: License :: OSI Approved :: MIT License
Classifier: Environment :: Console
Classifier: Operating System :: Microsoft :: Windows
Classifier: Operating System :: MacOS
Classifier: Operating System :: POSIX :: Linux
Requires-Python: >=3.6
License-File: LICENSE
Requires-Dist: conkits
Requires-Dist: requests
